luddite.py
luddite-1.0.4.dist-info/LICENSE
luddite-1.0.4.dist-info/METADATA
luddite-1.0.4.dist-info/WHEEL
luddite-1.0.4.dist-info/entry_points.txt
luddite-1.0.4.dist-info/top_level.txt
luddite-1.0.4.dist-info/RECORD
