Metadata-Version: 2.1
Name: luddite
Version: 1.0.4
Summary: Checks for out-of-date package versions
Home-page: https://github.com/jumptrading/luddite
Author: Wim Glenn
Author-email: hey@wimglenn.com
Classifier: Programming Language :: Python :: 2
Classifier: Programming Language :: Python :: 3
Classifier: Intended Audience :: Developers
Classifier: Topic :: Software Development :: Libraries
Classifier: Topic :: Utilities
License-File: LICENSE
Requires-Dist: packaging
Requires-Dist: colorama ; platform_system == "Windows"
Requires-Dist: futures ; python_version < "3.2"
Provides-Extra: dev
Requires-Dist: pytest >=3.6.3 ; extra == 'dev'
Requires-Dist: pytest-cov ; extra == 'dev'
Requires-Dist: pytest-mock ; extra == 'dev'
Requires-Dist: pytest-socket ; extra == 'dev'
